YYJ/ChatYYJ.py
YYJ/__core.py
YYJ/__init__.py
YYJ-1.0.2.dist-info/LICENSE
YYJ-1.0.2.dist-info/METADATA
YYJ-1.0.2.dist-info/WHEEL
YYJ-1.0.2.dist-info/top_level.txt
YYJ-1.0.2.dist-info/RECORD
